[
  {
    "ContainingType": "NoteAPI.Controllers.NoteController",
    "Method": "GetAllNotes",
    "RelativePath": "api/Note",
    "HttpMethod": "GET",
    "IsController": true,
    "Order": 0,
    "Parameters": [],
    "ReturnTypes": []
  },
  {
    "ContainingType": "NoteAPI.Controllers.NoteController",
    "Method": "AddNote",
    "RelativePath": "api/Note",
    "HttpMethod": "POST",
    "IsController": true,
    "Order": 0,
    "Parameters": [
      {
        "Name": "addnotedto",
        "Type": "NoteAPI.Models.AddNoteDto",
        "IsRequired": true
      }
    ],
    "ReturnTypes": []
  },
  {
    "ContainingType": "NoteAPI.Controllers.NoteController",
    "Method": "GetNoteById",
    "RelativePath": "api/Note/{id}",
    "HttpMethod": "GET",
    "IsController": true,
    "Order": 0,
    "Parameters": [
      {
        "Name": "id",
        "Type": "System.Guid",
        "IsRequired": true
      }
    ],
    "ReturnTypes": []
  },
  {
    "ContainingType": "NoteAPI.Controllers.NoteController",
    "Method": "UpdateNote",
    "RelativePath": "api/Note/{id}",
    "HttpMethod": "PUT",
    "IsController": true,
    "Order": 0,
    "Parameters": [
      {
        "Name": "id",
        "Type": "System.Guid",
        "IsRequired": true
      },
      {
        "Name": "updateNoteDto",
        "Type": "NoteAPI.Models.UpdateNoteDto",
        "IsRequired": true
      }
    ],
    "ReturnTypes": []
  },
  {
    "ContainingType": "NoteAPI.Controllers.NoteController",
    "Method": "DeleteNote",
    "RelativePath": "api/Note/{id}",
    "HttpMethod": "DELETE",
    "IsController": true,
    "Order": 0,
    "Parameters": [
      {
        "Name": "id",
        "Type": "System.Guid",
        "IsRequired": true
      }
    ],
    "ReturnTypes": []
  }
]